record_temp_analysis_nc/__init__.py
record_temp_analysis_nc/analysis.py
record_temp_analysis_nc-0.1.3.dist-info/LICENSE
record_temp_analysis_nc-0.1.3.dist-info/METADATA
record_temp_analysis_nc-0.1.3.dist-info/WHEEL
record_temp_analysis_nc-0.1.3.dist-info/top_level.txt
record_temp_analysis_nc-0.1.3.dist-info/RECORD
