Metadata-Version: 2.1
Name: record_temp_analysis_nc
Version: 0.1.3
Summary: A package to analyze and plot record-breaking temperatures.
Author: Bijan Fallah
Author-email: bijan.fallah@gmail.com
License: MIT
Classifier: Programming Language :: Python :: 3
Classifier: License :: OSI Approved :: MIT License
Classifier: Operating System :: OS Independent
Requires-Python: >=3.6
License-File: LICENSE
Requires-Dist: numpy
Requires-Dist: netCDF4
Requires-Dist: matplotlib
Requires-Dist: cartopy
Requires-Dist: tqdm
